solsys/__init__.py
solsys/core.py
solsys/correction.py
solsys/orbital_elements.py
solsys/transform.py
solsys/utils.py
solsys-1.1.0.dist-info/LICENSE.txt
solsys-1.1.0.dist-info/METADATA
solsys-1.1.0.dist-info/WHEEL
solsys-1.1.0.dist-info/top_level.txt
solsys-1.1.0.dist-info/RECORD
