Metadata-Version: 2.1
Name: solsys
Version: 1.1.0
Summary: A python package for calculating positions of Solar System objects
Home-page: https://github.com/behrouzz/solsys
Author: Behrouz Safari
Author-email: behrouz.safari@gmail.com
License: MIT
Platform: UNKNOWN
Classifier: Programming Language :: Python :: 3
Classifier: License :: OSI Approved :: MIT License
Classifier: Operating System :: OS Independent
Requires-Python: >=3.4
License-File: LICENSE.txt
Requires-Dist: numpy
